dhcpkit_technicolor/__init__.py
dhcpkit_technicolor/options.py
dhcpkit_technicolor/server_extension/__init__.py
dhcpkit_technicolor/server_extension/component.xml
dhcpkit_technicolor/server_extension/config.py
dhcpkit_technicolor-0.9.2.dist-info/DESCRIPTION.rst
dhcpkit_technicolor-0.9.2.dist-info/METADATA
dhcpkit_technicolor-0.9.2.dist-info/RECORD
dhcpkit_technicolor-0.9.2.dist-info/WHEEL
dhcpkit_technicolor-0.9.2.dist-info/entry_points.txt
dhcpkit_technicolor-0.9.2.dist-info/metadata.json
dhcpkit_technicolor-0.9.2.dist-info/top_level.txt
